[{"_id":"11_0","_rev":"7-379e4642af497a082867b5baf268d9e9","table":"task_table","task_name":"Verify Phone","page_id":11,"from_page_id":1493710443709,"parent_id":null,"user_id":"23d5c58422026c68269cd6e9ac22ca4a","header_template_id":"11_h","detail_template_id":"11_d","footer_template_id":"11_f","timeout_id":"","location_id":"","child_default_task_id":"","child_default_task_name":"","date_created":"2017-03-15T10:29:39.453Z","status":true,"category":"My Category","additional_data_fn":"","optional_data":{},"required_data":{},"offline_expiration_time":0,"display_if_empty":true,"type":{"public":{"public":"public"}},"image":"https://upload.wikimedia.org/wikipedia/commons/2/26/512pxIcon-sunset_photo_not_found.png","count_status":{"active":1,"unread":0},"count":{"active":1,"unread":0},"count_if":{"active":1,"unread":0},"defaults":{"parent":null,"next_child":null,"all_children":null,"user":"23d5c58422026c68269cd6e9ac22ca4a"}},{"_id":"13_0","_rev":"1-8162e7a91e37c94700e9cb86da2760f6","table":"task_table","task_name":"Game Screen","page_id":13,"from_page_id":2,"parent_id":"2_0","user_id":"da9976858d8bda52021754cf1909a327","header_template_id":"13_h","detail_template_id":"13_d","footer_template_id":"13_h","timeout_id":null,"location_id":null,"child_default_task_id":null,"child_default_task_name":null,"date_created":"2017-07-28T05:19:22.142Z","status":"true","category":"Menu","additional_data_fn":null,"optional_data":{},"required_data":{},"offline_expiration_time":0,"display_if_empty":"true","type":{"public":"public"},"image":"https://upload.wikimedia.org/wikipedia/commons/2/26/512pxIcon-sunset_photo_not_found.png","defaults":{"parent":null,"next_child":null,"all_children":null,"user":"da9976858d8bda52021754cf1909a327"}},{"_id":"14_0","_rev":"4-2fae50813b82870a87b4b5a1f22b8614","table":"task_table","task_name":"User edit screen","page_id":14,"from_page_id":2,"parent_id":"2_0","user_id":"ef451c4cdb5cc5fbcd5d14d936091430","header_template_id":"14_h","detail_template_id":"14_d","footer_template_id":"14_f","timeout_id":null,"location_id":null,"child_default_task_id":null,"child_default_task_name":null,"date_created":"2017-04-10T13:03:54.481Z","status":"true","category":"Edit_user","additional_data_fn":null,"optional_data":{},"required_data":{},"offline_expiration_time":0,"display_if_empty":"true","type":{"public":"public"},"image":"https://upload.wikimedia.org/wikipedia/commons/2/26/512pxIcon-sunset_photo_not_found.png","defaults":{"parent":null,"next_child":null,"all_children":null,"user":"ef451c4cdb5cc5fbcd5d14d936091430"}},{"_id":"15_0","_rev":"3-f2be9911f3a05a0351f0f592a77c7a97","table":"task_table","task_name":"edit_detail_short_form","page_id":15,"from_page_id":2,"parent_id":"2_0","user_id":"23d5c58422026c68269cd6e9ac22ca4a","header_template_id":"15_h","detail_template_id":"15_d","footer_template_id":"15_f","timeout_id":null,"location_id":null,"child_default_task_id":null,"child_default_task_name":null,"date_created":"2017-04-10T13:51:05.053Z","status":"true","category":"button","additional_data_fn":null,"optional_data":{},"required_data":{},"offline_expiration_time":0,"display_if_empty":true,"type":{"public":"public"},"image":"https://upload.wikimedia.org/wikipedia/commons/2/26/512pxIcon-sunset_photo_not_found.png","defaults":{"parent":null,"next_child":null,"all_children":null,"user":"23d5c58422026c68269cd6e9ac22ca4a"}},{"_id":"16_0","_rev":"5-12732c224da6af84845abf0b15ca19bd","table":"task_table","task_name":"edit_screen","user_id":"23d5c58422026c68269cd6e9ac22ca4a","page_id":16,"from_page_id":2,"parent_id":"2_0","header_template_id":"16_h","detail_template_id":"16_d","footer_template_id":"16_f","timeout_id":null,"child_default_task_id":null,"child_default_task_name":null,"date_created":"2017-04-05T09:28:55.806Z","type":{"public":"public","pubilc":"private"},"status":true,"category":"edit","additional_data_fn":"yes there is an additional function","optional_data":"\"\\\"\\\\\\\"{}\\\\\\\"\\\"\"","required_data":"\"\\\"\\\\\\\"{}\\\\\\\"\\\"\"","offline_expiration_time":"5000","display_if_empty":true,"image":"https://upload.wikimedia.org/wikipedia/commons/2/26/512pxIcon-sunset_photo_not_found.png"},{"_id":"17_0","_rev":"2-83470586139dd964771c53501f6a76c4","table":"task_table","task_name":"Search screen","user_id":"23d5c58422026c68269cd6e9ac22ca4a","page_id":17,"from_page_id":0,"parent_id":"2_0","header_template_id":"17_h","detail_template_id":"17_d","footer_template_id":"17_f","timeout_id":null,"child_default_task_id":null,"child_default_task_name":null,"date_created":"2017-04-05T09:28:55.806Z","type":{"public":"public"},"status":true,"category":"search","additional_data_fn":"yes there is an additional function","optional_data":"{}","required_data":"{}","offline_expiration_time":"5000","display_if_empty":true,"image":"https://upload.wikimedia.org/wikipedia/commons/2/26/512pxIcon-sunset_photo_not_found.png"},{"_id":"18_0","_rev":"3-1da2e9b05ab2a91f91fa72e430121dfc","table":"task_table","user_id":"23d5c58422026c68269cd6e9ac22ca4a","task_name":"Chatbot","page_id":18,"from_page_id":2,"header_template_id":"18_h","detail_template_id":"18_d","footer_template_id":"18_f","parent_id":"5_0","timeout_id":null,"location_ids":{},"child_default_task_id":null,"child_default_task_name":null,"date_created":"2017-03-15T10:29:39.453Z","category":"Book","status":"true","additional_data_fn":null,"optional_data":{},"required_data":{},"offline_expiration_time":0,"display_if_empty":"true","type":{"public":"public"},"image":"https://upload.wikimedia.org/wikipedia/commons/2/26/512pxIcon-sunset_photo_not_found.png"},{"_id":"19_0","_rev":"1-053fecb40b449e60df9c9ba40dba1a27","table":"task_table","user_id":"0a9b50963bc76018418ffd857d551ced","task_name":"addDetailToTask","page_id":19,"from_page_id":15,"header_template_id":"19_h","detail_template_id":"19_d","footer_template_id":"19_f","parent_id":"15_0","timeout_id":null,"location_ids":{},"child_default_task_id":null,"child_default_task_name":null,"date_created":"2017-08-01T12:32:20.826Z","category":"Book","status":"true","additional_data_fn":null,"optional_data":{},"required_data":{},"offline_expiration_time":0,"display_if_empty":"true","type":{"public":"public"},"image":"https://upload.wikimedia.org/wikipedia/commons/2/26/512pxIcon-sunset_photo_not_found.png"},{"_id":"1_0","_rev":"5-145aac6be5d49f29ba4a2bfa4820c162","table":"task_table","user_id":"23d5c58422026c68269cd6e9ac22ca4a","task_name":"Login","page_id":1,"from_page_id":0,"parent_id":null,"header_template_id":"1_h","detail_template_id":"1_d","footer_template_id":"1_f","timeout_id":null,"location_ids":{},"child_default_task_id":null,"child_default_task_name":"task_w_create_task","date_created":"2017-03-15T10:29:39.453Z","category":"Book","status":"true","additional_data_fn":null,"optional_data":{},"required_data":{},"offline_expiration_time":0,"display_if_empty":"true","type":{"public":"public"},"image":"https://upload.wikimedia.org/wikipedia/commons/2/26/512pxIcon-sunset_photo_not_found.png"},{"_id":"2_0","_rev":"13-671908f9b1e551956b93fff27f354a02","table":"task_table","task_name":"Categories","user_id":"23d5c58422026c68269cd6e9ac22ca4a","from_page_id":2,"page_id":2,"parent_id":"1_0","header_template_id":"2_h","detail_template_id":"2_d","footer_template_id":"2_f","timeout_id":null,"child_default_task_id":"cbf23f2101dfed59bdfe1b57f6bca9a5","child_default_task_name":"sub_category_task","date_created":"2017-03-15T10:29:39.453Z","type":{"public":"public"},"category":"Categories","additional_data_fn":"N/A","optional_data":"\"{}\"","required_data":"\"{}\"","offline_expiration_time":0,"display_if_empty":true,"image":"https://upload.wikimedia.org/wikipedia/commons/2/26/512pxIcon-sunset_photo_not_found.png","status":1},{"_id":"31_0","_rev":"1-3065188d0f9dbd9a55e56cd28c58ead3","table":"task_table","user_id":"23d5c58422026c68269cd6e9ac22ca4a","task_name":"Paradise Lost","page_id":31,"from_page_id":3,"parent_id":"3_0","header_template_id":"31_h","detail_template_id":"31_d","footer_template_id":"31_f","timeout_id":"05e8e44657c5ebfd8fd893ab1a366a9a","location_ids":{},"child_default_task_id":"ea1f86fe7bb573a145fb8e66ab08c49e","child_default_task_name":"task_w_create_task","date_created":"2017-03-15T10:29:39.453Z","category":"Book","status":"true","additional_data_fn":null,"optional_data":{},"required_data":{},"offline_expiration_time":0,"display_if_empty":"true","type":{"public":"public"},"image":"https://upload.wikimedia.org/wikipedia/commons/2/26/512pxIcon-sunset_photo_not_found.png","defaults":{"parent":null,"next_child":null,"all_children":null,"user":"23d5c58422026c68269cd6e9ac22ca4a"}},{"_id":"32_0","_rev":"2-43c3fdbd4dd3bd14f53cc46fcce46823","table":"task_table","user_id":"23d5c58422026c68269cd6e9ac22ca4a","task_name":"The Lean Startup","page_id":32,"from_page_id":3,"parent_id":"3_0","header_template_id":"31_h","detail_template_id":"31_d","footer_template_id":"31_f","timeout_id":null,"location_ids":{},"child_default_task_id":null,"child_default_task_name":"task_w_create_task","date_created":"2017-03-15T10:29:39.453Z","category":"Book","status":"true","additional_data_fn":null,"optional_data":{},"required_data":{},"offline_expiration_time":0,"display_if_empty":"true","type":{"public":"public"},"image":"https://upload.wikimedia.org/wikipedia/commons/2/26/512pxIcon-sunset_photo_not_found.png"},{"_id":"3_0","_rev":"1-c70ac907350f54bb3a3c2a007c3d1107","table":"task_table","user_id":"23d5c58422026c68269cd6e9ac22ca4a","task_name":"Books","page_id":3,"from_page_id":2,"to_page_id":0,"parent_id":"2_0","header_template_id":"3_h","detail_template_id":"3_d","footer_template_id":"3_f","timeout_id":null,"location_ids":{},"child_default_task_id":"80f37beb644eb8e365422286f051b5ca","child_default_task_name":"book_message_task","date_created":"2017-03-15T10:29:39.453Z","category":"Book","status":"true","additional_data_fn":null,"optional_data":{},"required_data":{},"offline_expiration_time":0,"display_if_empty":"true","type":{"public":"public"},"image":"https://upload.wikimedia.org/wikipedia/commons/2/26/512pxIcon-sunset_photo_not_found.png"},{"_id":"41_0","_rev":"1-315cbe3fee9e770d4eefc47ab07b8064","table":"task_table","user_id":"23d5c58422026c68269cd6e9ac22ca4a","task_name":"Germany","page_id":41,"parent_id":"4_0","header_template_id":"41_h","detail_template_id":"41_d","footer_template_id":"41_f","timeout_id":null,"location_ids":{},"child_default_task_id":null,"child_default_task_name":"task_w_create_task","date_created":"2017-03-15T10:29:39.453Z","category":"Book","status":"true","additional_data_fn":null,"optional_data":{},"required_data":{},"offline_expiration_time":0,"display_if_empty":"true","type":{"public":"public"},"image":"https://upload.wikimedia.org/wikipedia/commons/2/26/512pxIcon-sunset_photo_not_found.png"},{"_id":"42_0","_rev":"1-02a1c5e46ac5eb82ebcd9b2dd4b1b770","table":"task_table","user_id":"23d5c58422026c68269cd6e9ac22ca4a","task_name":"India","page_id":42,"parent_id":"4_0","header_template_id":"41_h","detail_template_id":"41_d","footer_template_id":"41_f","timeout_id":null,"location_ids":{},"child_default_task_id":null,"child_default_task_name":"task_w_create_task","date_created":"2017-03-15T10:29:39.453Z","category":"Book","status":"true","additional_data_fn":null,"optional_data":{},"required_data":{},"offline_expiration_time":0,"display_if_empty":"true","type":{"public":"public"},"image":"https://upload.wikimedia.org/wikipedia/commons/2/26/512pxIcon-sunset_photo_not_found.png"},{"_id":"47126a7129fa090a23a20d53c0025d87","_rev":"7-2ff640402b6b08de030f91b8a7c8715b","table":"task_table","task_name":"text_message_task","page_id":1496985127509,"from_page_id":0,"parent_id":0,"user_id":"10067e83ad5cd3b4e099d534bc28d76d","header_template_id":"51_h","detail_template_id":"51_d","footer_template_id":"51_f","timeout_id":null,"location_id":null,"child_default_task_id":null,"child_default_task_name":null,"date_created":"2017-03-23T06:32:36.647Z","status":"true","category":"SMS","additional_data_fn":null,"optional_data":{},"required_data":{},"offline_expiration_time":1,"display_if_empty":"true","type":{"public":"public"},"image":"https://upload.wikimedia.org/wikipedia/commons/2/26/512pxIcon-sunset_photo_not_found.png"},{"_id":"4_0","_rev":"1-119a4289b262fb525f43a39d26412037","table":"task_table","user_id":"23d5c58422026c68269cd6e9ac22ca4a","task_name":"Places","page_id":4,"from_page_id":2,"parent_id":"2_0","header_template_id":"4_h","detail_template_id":"4_d","footer_template_id":"4_f","timeout_id":null,"location_ids":{},"child_default_task_id":"8e780e0db7b8301ae2fda36ceda7b987","child_default_task_name":"travel_message_task","date_created":"2017-03-15T10:29:39.453Z","category":"Book","status":"true","additional_data_fn":null,"optional_data":{},"required_data":{},"offline_expiration_time":0,"display_if_empty":"true","type":{"public":"public"},"image":"https://upload.wikimedia.org/wikipedia/commons/2/26/512pxIcon-sunset_photo_not_found.png"},{"_id":"51_0","_rev":"1-5ad86e0595b454afdd77c678481323e9","table":"task_table","user_id":"23d5c58422026c68269cd6e9ac22ca4a","task_name":"Adam","page_id":51,"parent_id":"5_0","header_template_id":"51_h","detail_template_id":"51_d","footer_template_id":"51_f","timeout_id":null,"location_ids":{},"child_default_task_id":null,"child_default_task_name":"task_w_create_task","date_created":"2017-03-15T10:29:39.453Z","category":"Book","status":"true","additional_data_fn":null,"optional_data":{},"required_data":{},"offline_expiration_time":0,"display_if_empty":"true","type":{"public":"public"},"image":"https://upload.wikimedia.org/wikipedia/commons/2/26/512pxIcon-sunset_photo_not_found.png"},{"_id":"51fb167ca7670096ea62b4e9f913e7e5","_rev":"3-10263aaddaf84ac7f08acdce70466ba0","table":"task_table","task_name":"Chat by Types","user_id":"0a9b50963bc76018418ffd857d551ced","page_id":1499057617028,"from_page_id":2,"parent_id":"2_0","header_template_id":"9c96192922ad00f4ba81f45415b4bb7d","detail_template_id":"e835b9f969469024d7b820feea29c131","footer_template_id":"8f035001d4d22a7c6170a57020787ca7","timeout_id":"05e8e44657c5ebfd8fd893ab1a366a9a","location_id":"9813b20055279c8a89664542666bc176","child_default_task_id":"63270362fc0bdbc55379f9512d088c56","child_default_task_name":"message_task","date_created":"2017-07-03T04:53:37.123Z","type":{},"status":"true","category":"sub-category","additional_data_fn":null,"optional_data":{},"required_data":{},"offline_expiration_time":0,"display_if_empty":false,"count_status":{"active":1,"unread":0},"count":{"active":1,"unread":0},"count_if":{"active":1,"unread":0}},{"_id":"52_0","_rev":"1-94786df7d787e692747ffb959c6f598f","table":"task_table","user_id":"23d5c58422026c68269cd6e9ac22ca4a","task_name":"Ben","page_id":52,"header_template_id":"51_h","detail_template_id":"51_d","footer_template_id":"51_f","timeout_id":null,"parent_id":"5_0","location_ids":{},"child_default_task_id":null,"child_default_task_name":"task_w_create_task","date_created":"2017-03-15T10:29:39.453Z","category":"Book","status":"true","additional_data_fn":null,"optional_data":{},"required_data":{},"offline_expiration_time":0,"display_if_empty":"true","type":{"public":"public"},"image":"https://upload.wikimedia.org/wikipedia/commons/2/26/512pxIcon-sunset_photo_not_found.png"},{"_id":"53_0","_rev":"2-a75090310d4fa468103a99a4e5cfab1c","table":"task_table","user_id":"23d5c58422026c68269cd6e9ac22ca4a","task_name":"Clemens","page_id":53,"parent_id":"5_0","header_template_id":"51_h","detail_template_id":"51_d","footer_template_id":"51_f","timeout_id":null,"location_ids":{},"child_default_task_id":null,"child_default_task_name":"task_w_create_task","date_created":"2017-03-15T10:29:39.453Z","category":"Book","status":"true","additional_data_fn":null,"optional_data":{},"required_data":{},"offline_expiration_time":0,"display_if_empty":"true","type":{"public":"public"},"image":"https://upload.wikimedia.org/wikipedia/commons/2/26/512pxIcon-sunset_photo_not_found.png"},{"_id":"5_0","_rev":"8-7930de80522088423d0b23212df0567a","table":"task_table","user_id":"23d5c58422026c68269cd6e9ac22ca4a","task_name":"Text","page_id":5,"from_page_id":2,"header_template_id":"5_h","detail_template_id":"5_d","footer_template_id":"5_f","parent_id":"2_0","timeout_id":null,"location_ids":{},"child_default_task_id":"47126a7129fa090a23a20d53c0025d87","child_default_task_name":"text_message_task","date_created":"2017-03-15T10:29:39.453Z","category":"Book","status":"true","additional_data_fn":null,"optional_data":{},"required_data":{},"offline_expiration_time":0,"display_if_empty":"true","type":{"public":"public"},"image":"https://upload.wikimedia.org/wikipedia/commons/2/26/512pxIcon-sunset_photo_not_found.png"},{"_id":"61_0","_rev":"2-a5518aef4e4ddd849b8c9a9ac1846783","table":"task_table","user_id":"23d5c58422026c68269cd6e9ac22ca4a","task_name":"Adam","page_id":61,"parent_id":"6_0","header_template_id":"61_h","detail_template_id":"61_d","footer_template_id":"61_f","timeout_id":null,"location_ids":{},"child_default_task_id":null,"child_default_task_name":"task_w_create_task","date_created":"2017-03-15T10:29:39.453Z","category":"Book","status":"true","additional_data_fn":null,"optional_data":{},"required_data":{},"offline_expiration_time":0,"display_if_empty":"true","type":{"public":"public"},"image":"https://upload.wikimedia.org/wikipedia/commons/2/26/512pxIcon-sunset_photo_not_found.png"},{"_id":"62_0","_rev":"2-ddb496408e0c5eb4e121117c92a2e877","table":"task_table","user_id":"23d5c58422026c68269cd6e9ac22ca4a","task_name":"Ben","page_id":62,"parent_id":"6_0","header_template_id":"61_h","detail_template_id":"61_d","footer_template_id":"61_f","timeout_id":null,"location_ids":{},"child_default_task_id":null,"child_default_task_name":"task_w_create_task","date_created":"2017-03-15T10:29:39.453Z","category":"Book","status":"active","additional_data_fn":null,"optional_data":{},"required_data":{},"offline_expiration_time":0,"display_if_empty":"true","type":{"public":"public"},"image":"https://upload.wikimedia.org/wikipedia/commons/2/26/512pxIcon-sunset_photo_not_found.png"},{"_id":"63270362fc0bdbc55379f9512d088c56","_rev":"1-aa7152951ec05eb05ce4b4343480f508","table":"task_table","task_name":"message_task","page_id":769038,"from_page_id":769038,"parent_id":"cbf23f2101dfed59bdfe1b57f6bca9a5","user_id":"23d5c58422026c68269cd6e9ac22ca4a","header_template_id":"9c96192922ad00f4ba81f45415a028c8","detail_template_id":"4b8e310c44ca4e6e04aafd81594bfc5c","footer_template_id":"8f035001d4d22a7c6170a57020635378","timeout_id":null,"location_id":null,"child_default_task_id":null,"child_default_task_name":null,"date_created":"2017-04-03T11:02:39.970Z","status":"true","category":"message","additional_data_fn":null,"optional_data":{},"required_data":{},"offline_expiration_time":1,"display_if_empty":true,"type":{"public":"public"},"image":"https://upload.wikimedia.org/wikipedia/commons/2/26/512pxIcon-sunset_photo_not_found.png","defaults":{"parent":null,"next_child":null,"all_children":null,"user":"23d5c58422026c68269cd6e9ac22ca4a"}},{"_id":"63_0","_rev":"2-a292243ecc5df730e668e37579e87760","table":"task_table","user_id":"23d5c58422026c68269cd6e9ac22ca4a","task_name":"Clemens","page_id":63,"parent_id":"6_0","header_template_id":"61_h","detail_template_id":"61_d","footer_template_id":"61_f","timeout_id":null,"location_ids":{},"child_default_task_id":null,"child_default_task_name":"task_w_create_task","date_created":"2017-03-15T10:29:39.453Z","category":"Book","status":"active","additional_data_fn":null,"optional_data":{},"required_data":{},"offline_expiration_time":0,"display_if_empty":"true","type":{"public":"public"},"image":"https://upload.wikimedia.org/wikipedia/commons/2/26/512pxIcon-sunset_photo_not_found.png"},{"_id":"6_0","_rev":"7-693d1197c42127853fe2f551258a1d8f","table":"task_table","user_id":"23d5c58422026c68269cd6e9ac22ca4a","task_name":"Chat","page_id":6,"from_page_id":2,"header_template_id":"6_h","detail_template_id":"6_d","footer_template_id":"6_f","parent_id":"2_0","timeout_id":null,"location_ids":{},"child_default_task_id":"ea1f86fe7bb573a145fb8e66ab08c49e","child_default_task_name":"chat_message_task","date_created":"2017-03-15T10:29:39.453Z","category":"Chat","status":1,"additional_data_fn":null,"optional_data":{},"required_data":{},"offline_expiration_time":0,"display_if_empty":1,"type":{"public":"public"},"image":"https://upload.wikimedia.org/wikipedia/commons/2/26/512pxIcon-sunset_photo_not_found.png"},{"_id":"80f37beb644eb8e365422286f051b5ca","_rev":"3-70026104b722db0ba8181693a456493a","table":"task_table","task_name":"book_message_task","page_id":1497616619194,"from_page_id":0,"parent_id":"3_0","user_id":"23d5c58422026c68269cd6e9ac22ca4a","header_template_id":"31_h","detail_template_id":"31_d","footer_template_id":"31_f","timeout_id":null,"location_id":{"9813b20055279c8a89664542666bc176":{"_id":"9813b20055279c8a89664542666bc176","_rev":"1-cefeb42a72cda445c31fe7e224a945f8","location_name":"Philadelphia","location_type":"City","location_data":{"lat":40.0046684,"lon":-75.258117,"dist":0,"web":"https://en.wikipedia.org/wiki/Philadelphia"}}},"child_default_task_id":null,"child_default_task_name":null,"date_created":"2017-03-28T06:33:44.904Z","status":"true","category":"Book","additional_data_fn":null,"optional_data":{},"required_data":{},"offline_expiration_time":0,"display_if_empty":true,"type":{"public":"public"},"image":"https://upload.wikimedia.org/wikipedia/commons/2/26/512pxIcon-sunset_photo_not_found.png"},{"_id":"8e780e0db7b8301ae2fda36ceda7b987","_rev":"3-96bbaff6286626bb79d47e42d53711cf","table":"task_table","task_name":"travel_message_task","page_id":1497616676014,"from_page_id":0,"parent_id":"4_0","user_id":"23d5c58422026c68269cd6e9ac22ca4a","header_template_id":"41_h","detail_template_id":"41_d","footer_template_id":"41_f","timeout_id":null,"location_id":null,"child_default_task_id":null,"child_default_task_name":null,"date_created":"2017-03-31T09:22:50.256Z","status":"true","category":"Books","additional_data_fn":null,"optional_data":{},"required_data":{},"offline_expiration_time":0,"display_if_empty":"true","type":{"public":"public"},"image":"https://upload.wikimedia.org/wikipedia/commons/2/26/512pxIcon-sunset_photo_not_found.png","defaults":{"parent":null,"next_child":null,"all_children":null,"user":"23d5c58422026c68269cd6e9ac22ca4a"}},{"_id":"99_0","_rev":"1-7a9787083633789145f4b42f70a9dcf4","table":"task_table","task_name":"user_chatbot_message_task","page_id":1496985127509,"from_page_id":0,"parent_id":0,"user_id":"10067e83ad5cd3b4e099d534bc28d76d","header_template_id":"99_h","detail_template_id":"99_d","footer_template_id":"99_f","timeout_id":null,"location_id":null,"child_default_task_id":null,"child_default_task_name":null,"date_created":"2017-03-23T06:32:36.647Z","status":"true","category":"SMS","additional_data_fn":null,"optional_data":{},"required_data":{},"offline_expiration_time":1,"display_if_empty":"true","type":{"public":"public"},"image":""},{"_id":"cbf23f2101dfed59bdfe1b57f6bca9a5","_rev":"2-7607033c935019c8de34bdb041003e1b","table":"task_table","task_name":"sub_category_task","page_id":948581,"from_page_id":2,"parent_id":"2_0","user_id":"23d5c58422026c68269cd6e9ac22ca4a","header_template_id":"9c96192922ad00f4ba81f45415b4bb7d","detail_template_id":"e835b9f969469024d7b820feea29c131","footer_template_id":"8f035001d4d22a7c6170a57020787ca7","timeout_id":"05e8e44657c5ebfd8fd893ab1a366a9a","location_id":"9813b20055279c8a89664542666bc176","child_default_task_id":"63270362fc0bdbc55379f9512d088c56","child_default_task_name":"message_task","date_created":"2017-04-03T06:58:07.756Z","status":"true","category":"sub-category","additional_data_fn":null,"optional_data":{},"required_data":{},"offline_expiration_time":0,"display_if_empty":true,"type":{"public":"public"},"image":"https://upload.wikimedia.org/wikipedia/commons/2/26/512pxIcon-sunset_photo_not_found.png","defaults":{"parent":null,"next_child":null,"all_children":null,"user":"23d5c58422026c68269cd6e9ac22ca4a"}},{"_id":"d38db64a881913c1b6227dcdbf7539ec","_rev":"1-777e5a7074113c9e77358367797da71c","table":"task_table","task_name":"Clemens ","user_id":"10067e83ad5cd3b4e099d534bc28d76d","page_id":1496821289391,"from_page_id":5,"parent_id":"5_0","header_template_id":"51_h","detail_template_id":"51_d","footer_template_id":"51_f","timeout_id":null,"location_id":null,"child_default_task_id":null,"child_default_task_name":null,"date_created":"2017-06-07T07:41:29.527Z","type":{"public":"public"},"status":"true","category":"SMS","additional_data_fn":null,"optional_data":{},"required_data":{},"offline_expiration_time":1,"display_if_empty":"true","count_status":{"active":1,"unread":0},"count":{"active":1,"unread":0},"count_if":{"active":1,"unread":0}},{"_id":"ea1f86fe7bb573a145fb8e66ab08c49e","_rev":"4-2e21ce304638509b6244b29301ce74df","table":"task_table","task_name":"chat_message_task","page_id":1496985323154,"from_page_id":0,"parent_id":0,"user_id":"10067e83ad5cd3b4e099d534bc28d76d","header_template_id":"61_h","detail_template_id":"61_d","footer_template_id":"61_f","timeout_id":null,"location_id":null,"child_default_task_id":null,"child_default_task_name":null,"date_created":"2017-03-23T06:32:36.647Z","status":"true","category":"SMS","additional_data_fn":null,"optional_data":{},"required_data":{},"offline_expiration_time":1,"display_if_empty":"true","type":{"public":"public"},"image":"https://upload.wikimedia.org/wikipedia/commons/2/26/512pxIcon-sunset_photo_not_found.png"}]